AUTHORS.txt
LICENSE.txt
MANIFEST.in
README.rst
setup.cfg
setup.py
mojo/__init__.py
mojo/navigation/__init__.py
mojo/navigation/admin.py
mojo/navigation/apps.py
mojo/navigation/managers.py
mojo/navigation/models.py
mojo/navigation/settings.py
mojo/navigation/tests/__init__.py
mojo/navigation/tests/manage.py
mojo/navigation/tests/models.py
mojo/navigation/tests/settings.py
mojo/navigation/tests/test_admin.py
mojo/navigation/tests/test_managers.py
mojo/navigation/tests/test_models.py
mojo/navigation/tests/urls.py
mojo_navigation.egg-info/PKG-INFO
mojo_navigation.egg-info/SOURCES.txt
mojo_navigation.egg-info/dependency_links.txt
mojo_navigation.egg-info/requires.txt
mojo_navigation.egg-info/top_level.txt