Metadata-Version: 1.1
Name: mojo-navigation
Version: 0.0.1
Summary: Django app managing simple navigation.
Home-page: http://www.revsquare.com
Author: Guillaume Pousseo
Author-email: guillaumepousseo@revsquare.com
License: MIT License
Platform: OS Independent
Classifier: Development Status :: 5 - Production/Stable
Classifier: Environment :: Web Environment
Classifier: Framework :: Django
Classifier: Framework :: Django :: 1.7
Classifier: Framework :: Django :: 1.8
Classifier: Intended Audience :: Developers
Classifier: License :: OSI Approved :: MIT License
Classifier: Operating System :: OS Independent
Classifier: Programming Language :: Python
Classifier: Programming Language :: Python :: 2.7
Classifier: Programming Language :: Python :: 3.4
Classifier: Programming Language :: Python :: 3.5
